LICENSE
MANIFEST.in
README.md
README.rst
setup.py
scipy_tweaks/__init__.py
scipy_tweaks/idseqs_to_mask.py
scipy_tweaks.egg-info/PKG-INFO
scipy_tweaks.egg-info/SOURCES.txt
scipy_tweaks.egg-info/dependency_links.txt
scipy_tweaks.egg-info/requires.txt
scipy_tweaks.egg-info/top_level.txt
scipy_tweaks.egg-info/zip-safe
test/__init__.py
test/test_idseqs_to_mask.py