Metadata-Version: 1.2
Name: scipy-tweaks
Version: 0.1.3
Summary: Utility functions for scipy.
Home-page: http://github.com/ulf1/scipy-tweaks
Author: Ulf Hamster
Author-email: 554c46@gmail.com
License: Apache License 2.0
Platform: UNKNOWN
Requires-Python: >=3.6
